podder_task_foundation/__init__.py
podder_task_foundation/context.py
podder_task_foundation/file.py
podder_task_foundation/mode.py
podder_task_foundation/settings.py
podder_task_foundation/task.py
podder_task_foundation/api/__init__.py
podder_task_foundation/api/grpc_server.py
podder_task_foundation/api/task_api_executor.py
podder_task_foundation/api/task_grpc_wrapper.py
podder_task_foundation/api/protos/__init__.py
podder_task_foundation/api/protos/pipeline_framework_pb2.py
podder_task_foundation/api/protos/pipeline_framework_pb2_grpc.py
podder_task_foundation/config/__init__.py
podder_task_foundation/config/config.py
podder_task_foundation/config/file.py
podder_task_foundation/config/parsers/__init__.py
podder_task_foundation/config/parsers/base.py
podder_task_foundation/config/parsers/ini.py
podder_task_foundation/config/parsers/json.py
podder_task_foundation/config/parsers/yaml.py
podder_task_foundation/exceptions/__init__.py
podder_task_foundation/exceptions/ambiguous_parameter_exception.py
podder_task_foundation/exceptions/config_parse_exception.py
podder_task_foundation/exceptions/directory_not_found_exception.py
podder_task_foundation/exceptions/environment_variable_missing_exception.py
podder_task_foundation/exceptions/file_not_found_exception.py
podder_task_foundation/exceptions/podder_task_exception.py
podder_task_foundation/log/__init__.py
podder_task_foundation/log/log_setting.py
podder_task_foundation/log/stream_to_logger.py
podder_task_foundation/log/task_logger.py
podder_task_foundation/log/loggers/__init__.py
podder_task_foundation/log/loggers/base_logger.py
podder_task_foundation/log/loggers/server_logger.py
podder_task_foundation/log/loggers/task_logger.py
podder_task_foundation/objects/__init__.py
podder_task_foundation/objects/object.py
podder_task_foundation/objects/data/__init__.py
podder_task_foundation/objects/data/data.py
podder_task_foundation/objects/data/file.py
podder_task_foundation/objects/data_transfer_object_group/__init__.py
podder_task_foundation-0.1.0.dist-info/METADATA
podder_task_foundation-0.1.0.dist-info/WHEEL
podder_task_foundation-0.1.0.dist-info/top_level.txt
podder_task_foundation-0.1.0.dist-info/RECORD
