Metadata-Version: 2.1
Name: podder-task-foundation
Version: 0.1.0
Summary: UNKNOWN
Home-page: https://podder.ai/
Author: podder-ai
Author-email: UNKNOWN
License: UNKNOWN
Platform: UNKNOWN
Requires-Dist: PyYAML (==5.1)
Requires-Dist: pytest (==4.3.1)
Requires-Dist: pytest-mock (==1.11.1)
Requires-Dist: requests (==2.22.0)
Requires-Dist: python-dotenv (==0.10.1)
Requires-Dist: colorlog (==4.0.2)
Requires-Dist: googleapis-common-protos (==1.6.0)
Requires-Dist: grpcio (==1.24.1)
Requires-Dist: grpcio-tools (==1.18.0)
Requires-Dist: protobuf (==3.10.0)
Requires-Dist: filetype (==1.0.5)
